.DS_Store
pyspotless/__init__.py
pyspotless/offline.py
pyspotless/pyspotless.py
pyspotless-1.0.3.dist-info/DESCRIPTION.rst
pyspotless-1.0.3.dist-info/METADATA
pyspotless-1.0.3.dist-info/RECORD
pyspotless-1.0.3.dist-info/WHEEL
pyspotless-1.0.3.dist-info/metadata.json
pyspotless-1.0.3.dist-info/top_level.txt
