Metadata-Version: 2.0
Name: pyspotless
Version: 1.0.3
Summary: A client library for integrating spotlessdata.com into Python applications
Home-page: https://spotlessdata.com/docs/using-spotless-python
Author: Spotless Data
Author-email: team@spotlessdata.com
License: MIT
Keywords: spotless datacleansing
Platform: UNKNOWN
Classifier: Development Status :: 5 - Production/Stable
Classifier: Intended Audience :: Developers
Classifier: Topic :: Software Development :: Libraries
Classifier: License :: OSI Approved :: MIT License
Classifier: Programming Language :: Python :: 3.4
Classifier: Programming Language :: Python :: 3.5
Classifier: Programming Language :: Python :: 3.6
